openaitrans/__init__.py
openaitrans/translator.py
openaitrans-0.1.1.dist-info/licenses/LICENSE
openaitrans-0.1.1.dist-info/METADATA
openaitrans-0.1.1.dist-info/WHEEL
openaitrans-0.1.1.dist-info/top_level.txt
openaitrans-0.1.1.dist-info/RECORD
